optmanage/__init__.py
optmanage/manager.py
optmanage/option.py
optmanage/py.typed
optmanage-1.1.1.dist-info/LICENSE
optmanage-1.1.1.dist-info/METADATA
optmanage-1.1.1.dist-info/WHEEL
optmanage-1.1.1.dist-info/top_level.txt
optmanage-1.1.1.dist-info/RECORD
