Metadata-Version: 2.1
Name: optmanage
Version: 1.1.1
Summary: A library to create flexible option managers.
Home-page: https://github.com/hashberg-io/optmanage
Author: hashberg
Author-email: sg495@users.noreply.github.com
Project-URL: Bug Tracker, https://github.com/hashberg-io/optmanage/issues
Classifier: Development Status :: 4 - Beta
Classifier: Programming Language :: Python :: 3.12
Classifier: Programming Language :: Python :: 3.11
Classifier: Programming Language :: Python :: 3.10
Classifier: Programming Language :: Python :: 3.9
Classifier: Programming Language :: Python :: 3.8
Classifier: Operating System :: OS Independent
Classifier: Natural Language :: English
Classifier: Typing :: Typed
Requires-Python: >=3.10
License-File: LICENSE
Requires-Dist: typing-extensions >=4.6.0
Requires-Dist: typing-validation >=1.2.4
Provides-Extra: dev
Requires-Dist: mypy ; extra == 'dev'
Requires-Dist: pylint ; extra == 'dev'
Requires-Dist: pytest ; extra == 'dev'
Requires-Dist: pytest-cov ; extra == 'dev'
